finrobot/__init__.py
finrobot/toolkits.py
finrobot/utils.py
finrobot/agents/__init__.py
finrobot/agents/agent_library.py
finrobot/agents/prompts.py
finrobot/agents/utils.py
finrobot/agents/workflow.py
finrobot/data_source/__init__.py
finrobot/data_source/finnhub_utils.py
finrobot/data_source/finnlp_utils.py
finrobot/data_source/fmp_utils.py
finrobot/data_source/reddit_utils.py
finrobot/data_source/sec_utils.py
finrobot/data_source/yfinance_utils.py
finrobot/functional/__init__.py
finrobot/functional/analyzer.py
finrobot/functional/charting.py
finrobot/functional/coding.py
finrobot/functional/quantitative.py
finrobot/functional/rag.py
finrobot/functional/reportlab.py
finrobot/functional/text.py
FinRobot-0.1.5.dist-info/LICENSE
FinRobot-0.1.5.dist-info/METADATA
FinRobot-0.1.5.dist-info/WHEEL
FinRobot-0.1.5.dist-info/top_level.txt
FinRobot-0.1.5.dist-info/RECORD
